{"props":{"itemprops_get_response":{"item_props":{"item_prop":[{"child_template":"","is_color_prop":false,"is_enum_prop":true,"is_input_prop":false,"is_item_prop":false,"is_key_prop":false,"is_sale_prop":true,"multi":true,"must":false,"name":"尺码","parent_pid":0,"parent_vid":0,"pid":20509,"sort_order":0,"status":"normal"}]},"last_modified":"2018-07-26 16:57:57","request_id":"uswh5qd55cz"}},"propvalues":{"itempropvalues_get_response":{"last_modified":"2018-07-26 16:57:57","prop_values":{"prop_value":[{"cid":125632002,"name":"ZH240","name_alias":"ZH240","pid":20509,"prop_name":"尺码","sort_order":0,"status":"normal","vid":43520870},{"cid":125632002,"name":"ZH250","name_alias":"ZH250","pid":20509,"prop_name":"尺码","sort_order":0,"status":"normal","vid":6757828},{"cid":125632002,"name":"ZH255","name_alias":"ZH255","pid":20509,"prop_name":"尺码","sort_order":0,"status":"normal","vid":20120990},{"cid":125632002,"name":"ZH260","name_alias":"ZH260","pid":20509,"prop_name":"尺码","sort_order":0,"status":"normal","vid":20159713},{"cid":125632002,"name":"ZH265","name_alias":"ZH265","pid":20509,"prop_name":"尺码","sort_order":0,"status":"normal","vid":20193071},{"cid":125632002,"name":"ZH270","name_alias":"ZH270","pid":20509,"prop_name":"尺码","sort_order":0,"status":"normal","vid":6755761},{"cid":125632002,"name":"ZH275","name_alias":"ZH275","pid":20509,"prop_name":"尺码","sort_order":0,"status":"normal","vid":20200841},{"cid":125632002,"name":"ZH280","name_alias":"ZH280","pid":20509,"prop_name":"尺码","sort_order":0,"status":"normal","vid":6754152},{"cid":125632002,"name":"ZH285","name_alias":"ZH285","pid":20509,"prop_name":"尺码","sort_order":0,"status":"normal","vid":6753824},{"cid":125632002,"name":"ZH290","name_alias":"ZH290","pid":20509,"prop_name":"尺码","sort_order":0,"status":"normal","vid":66383278},{"cid":125632002,"name":"ZH295","name_alias":"ZH295","pid":20509,"prop_name":"尺码","sort_order":0,"status":"normal","vid":49436337},{"cid":125632002,"name":"ZH300","name_alias":"ZH300","pid":20509,"prop_name":"尺码","sort_order":0,"status":"normal","vid":8331319},{"cid":125632002,"name":"ZH305","name_alias":"ZH305","pid":20509,"prop_name":"尺码","sort_order":0,"status":"normal","vid":76120331},{"cid":125632002,"name":"zh245","name_alias":"zh245","pid":20509,"prop_name":"尺码","sort_order":0,"status":"normal","vid":10746229},{"cid":125632002,"name":"UK1","name_alias":"1","pid":20509,"prop_name":"尺码","sort_order":1,"status":"normal","vid":11797810},{"cid":125632002,"name":"UK1.5","name_alias":"1.5","pid":20509,"prop_name":"尺码","sort_order":1,"status":"normal","vid":8403789},{"cid":125632002,"name":"UK2","name_alias":"2","pid":20509,"prop_name":"尺码","sort_order":2,"status":"normal","vid":11800449},{"cid":125632002,"name":"UK2.5","name_alias":"2.5","pid":20509,"prop_name":"尺码","sort_order":3,"status":"normal","vid":20852374},{"cid":125632002,"name":"UK3","name_alias":"3","pid":20509,"prop_name":"尺码","sort_order":4,"status":"normal","vid":6546731},{"cid":125632002,"name":"UK3.5","name_alias":"3.5","pid":20509,"prop_name":"尺码","sort_order":5,"status":"normal","vid":662626471},{"cid":125632002,"name":"UK4.5","name_alias":"4.5","pid":20509,"prop_name":"尺码","sort_order":7,"status":"normal","vid":662626477},{"cid":125632002,"name":"UK5","name_alias":"5","pid":20509,"prop_name":"尺码","sort_order":8,"status":"normal","vid":7654174},{"cid":125632002,"name":"uk5.5","name_alias":"5.5","pid":20509,"prop_name":"尺码","sort_order":9,"status":"normal","vid":365174445},{"cid":125632002,"name":"uk6","name_alias":"6","pid":20509,"prop_name":"尺码","sort_order":10,"status":"normal","vid":12624364},{"cid":125632002,"name":"UK6.5","name_alias":"6.5","pid":20509,"prop_name":"尺码","sort_order":11,"status":"normal","vid":662626481},{"cid":125632002,"name":"uk7","name_alias":"7","pid":20509,"prop_name":"尺码","sort_order":12,"status":"normal","vid":12880590},{"cid":125632002,"name":"UK7.5","name_alias":"7.5","pid":20509,"prop_name":"尺码","sort_order":13,"status":"normal","vid":662626483},{"cid":125632002,"name":"UK8.5","name_alias":"8.5","pid":20509,"prop_name":"尺码","sort_order":15,"status":"normal","vid":662626485},{"cid":125632002,"name":"uk9","name_alias":"9","pid":20509,"prop_name":"尺码","sort_order":16,"status":"normal","vid":32859044},{"cid":125632002,"name":"UK9.5","name_alias":"9.5","pid":20509,"prop_name":"尺码","sort_order":17,"status":"normal","vid":344154618},{"cid":125632002,"name":"UK10","name_alias":"10","pid":20509,"prop_name":"尺码","sort_order":18,"status":"normal","vid":7285415},{"cid":125632002,"name":"UK10.5","name_alias":"10.5","pid":20509,"prop_name":"尺码","sort_order":19,"status":"normal","vid":662626457},{"cid":125632002,"name":"UK11.5","name_alias":"11.5","pid":20509,"prop_name":"尺码","sort_order":19,"status":"normal","vid":762602213},{"cid":125632002,"name":"UK12.5","name_alias":"12.5","pid":20509,"prop_name":"尺码","sort_order":22,"status":"normal","vid":801304001},{"cid":125632002,"name":"UK14","name_alias":"14","pid":20509,"prop_name":"尺码","sort_order":22,"status":"normal","vid":65356191},{"cid":125632002,"name":"UK13","name_alias":"13","pid":20509,"prop_name":"尺码","sort_order":23,"status":"normal","vid":16667344},{"cid":125632002,"name":"UK13.5","name_alias":"13.5","pid":20509,"prop_name":"尺码","sort_order":24,"status":"normal","vid":801304002},{"cid":125632002,"name":"US1","name_alias":"1","pid":20509,"prop_name":"尺码","sort_order":33,"status":"normal","vid":12036912},{"cid":125632002,"name":"US1.5","name_alias":"1.5","pid":20509,"prop_name":"尺码","sort_order":34,"status":"normal","vid":399428077},{"cid":125632002,"name":"US2","name_alias":"2","pid":20509,"prop_name":"尺码","sort_order":35,"status":"normal","vid":6651814},{"cid":125632002,"name":"US2.5","name_alias":"2.5","pid":20509,"prop_name":"尺码","sort_order":36,"status":"normal","vid":399428078},{"cid":125632002,"name":"us3","name_alias":"3","pid":20509,"prop_name":"尺码","sort_order":37,"status":"normal","vid":12674145},{"cid":125632002,"name":"US3.5","name_alias":"3.5","pid":20509,"prop_name":"尺码","sort_order":38,"status":"normal","vid":82811824},{"cid":125632002,"name":"US4","name_alias":"4","pid":20509,"prop_name":"尺码","sort_order":39,"status":"normal","vid":10504551},{"cid":125632002,"name":"US4.5","name_alias":"4.5","pid":20509,"prop_name":"尺码","sort_order":40,"status":"normal","vid":436304628},{"cid":125632002,"name":"US5","name_alias":"5","pid":20509,"prop_name":"尺码","sort_order":41,"status":"normal","vid":6240817},{"cid":125632002,"name":"US5.5","name_alias":"5.5","pid":20509,"prop_name":"尺码","sort_order":42,"status":"normal","vid":383226141},{"cid":125632002,"name":"us6","name_alias":"6","pid":20509,"prop_name":"尺码","sort_order":43,"status":"normal","vid":8226873},{"cid":125632002,"name":"us6.5","name_alias":"6.5","pid":20509,"prop_name":"尺码","sort_order":44,"status":"normal","vid":67782966},{"cid":125632002,"name":"us7","name_alias":"7","pid":20509,"prop_name":"尺码","sort_order":45,"status":"normal","vid":12674166},{"cid":125632002,"name":"US7.5","name_alias":"7.5","pid":20509,"prop_name":"尺码","sort_order":46,"status":"normal","vid":69375091},{"cid":125632002,"name":"us8","name_alias":"8","pid":20509,"prop_name":"尺码","sort_order":47,"status":"normal","vid":12674322},{"cid":125632002,"name":"us8.5","name_alias":"8.5","pid":20509,"prop_name":"尺码","sort_order":48,"status":"normal","vid":133866457},{"cid":125632002,"name":"us9","name_alias":"9","pid":20509,"prop_name":"尺码","sort_order":49,"status":"normal","vid":12674203},{"cid":125632002,"name":"US9.5","name_alias":"9.5","pid":20509,"prop_name":"尺码","sort_order":50,"status":"normal","vid":383226142},{"cid":125632002,"name":"us10","name_alias":"10","pid":20509,"prop_name":"尺码","sort_order":51,"status":"normal","vid":12674541},{"cid":125632002,"name":"us10.5","name_alias":"10.5","pid":20509,"prop_name":"尺码","sort_order":52,"status":"normal","vid":81668144},{"cid":125632002,"name":"US11","name_alias":"11","pid":20509,"prop_name":"尺码","sort_order":53,"status":"normal","vid":10145050},{"cid":125632002,"name":"US11.5","name_alias":"11.5","pid":20509,"prop_name":"尺码","sort_order":54,"status":"normal","vid":411978872},{"cid":125632002,"name":"US12","name_alias":"12","pid":20509,"prop_name":"尺码","sort_order":55,"status":"normal","vid":11768567},{"cid":125632002,"name":"US12.5","name_alias":"12.5","pid":20509,"prop_name":"尺码","sort_order":56,"status":"normal","vid":399428075},{"cid":125632002,"name":"us14","name_alias":"14","pid":20509,"prop_name":"尺码","sort_order":57,"status":"normal","vid":12677498},{"cid":125632002,"name":"EUR22","name_alias":"22","pid":20509,"prop_name":"尺码","sort_order":64,"status":"normal","vid":107568607},{"cid":125632002,"name":"EUR22.5","name_alias":"22.5","pid":20509,"prop_name":"尺码","sort_order":65,"status":"normal","vid":801304003},{"cid":125632002,"name":"EUR23","name_alias":"23","pid":20509,"prop_name":"尺码","sort_order":66,"status":"normal","vid":672896046},{"cid":125632002,"name":"EUR23.5","name_alias":"23.5","pid":20509,"prop_name":"尺码","sort_order":67,"status":"normal","vid":801304004},{"cid":125632002,"name":"EUR24","name_alias":"24","pid":20509,"prop_name":"尺码","sort_order":67,"status":"normal","vid":152524919},{"cid":125632002,"name":"EUR24.5","name_alias":"24.5","pid":20509,"prop_name":"尺码","sort_order":68,"status":"normal","vid":801304005},{"cid":125632002,"name":"EUR25","name_alias":"25","pid":20509,"prop_name":"尺码","sort_order":68,"status":"normal","vid":155046983},{"cid":125632002,"name":"EUR25.5","name_alias":"25.5","pid":20509,"prop_name":"尺码","sort_order":69,"status":"normal","vid":801304006},{"cid":125632002,"name":"EUR26","name_alias":"26","pid":20509,"prop_name":"尺码","sort_order":69,"status":"normal","vid":55691955},{"cid":125632002,"name":"EUR26.5","name_alias":"26.5","pid":20509,"prop_name":"尺码","sort_order":70,"status":"normal","vid":801304007},{"cid":125632002,"name":"EUR27","name_alias":"27","pid":20509,"prop_name":"尺码","sort_order":70,"status":"normal","vid":662626358},{"cid":125632002,"name":"EUR27.5","name_alias":"27.5","pid":20509,"prop_name":"尺码","sort_order":71,"status":"normal","vid":801304008},{"cid":125632002,"name":"EUR28","name_alias":"28","pid":20509,"prop_name":"尺码","sort_order":71,"status":"normal","vid":662626359},{"cid":125632002,"name":"EUR28.5","name_alias":"28.5","pid":20509,"prop_name":"尺码","sort_order":72,"status":"normal","vid":801304009},{"cid":125632002,"name":"EUR29","name_alias":"29","pid":20509,"prop_name":"尺码","sort_order":72,"status":"normal","vid":662626360},{"cid":125632002,"name":"EUR29.5","name_alias":"29.5","pid":20509,"prop_name":"尺码","sort_order":73,"status":"normal","vid":801304010},{"cid":125632002,"name":"EUR30","name_alias":"30","pid":20509,"prop_name":"尺码","sort_order":73,"status":"normal","vid":444706729},{"cid":125632002,"name":"EUR30.5","name_alias":"30.5","pid":20509,"prop_name":"尺码","sort_order":74,"status":"normal","vid":672896047},{"cid":125632002,"name":"EUR31","name_alias":"31","pid":20509,"prop_name":"尺码","sort_order":75,"status":"normal","vid":662626362},{"cid":125632002,"name":"EUR31.5","name_alias":"31.5","pid":20509,"prop_name":"尺码","sort_order":76,"status":"normal","vid":672896048},{"cid":125632002,"name":"EUR32","name_alias":"32","pid":20509,"prop_name":"尺码","sort_order":77,"status":"normal","vid":73406764},{"cid":125632002,"name":"EUR32.5","name_alias":"32.5","pid":20509,"prop_name":"尺码","sort_order":78,"status":"normal","vid":672896049},{"cid":125632002,"name":"EUR33","name_alias":"33","pid":20509,"prop_name":"尺码","sort_order":79,"status":"normal","vid":662626364},{"cid":125632002,"name":"EUR33.5","name_alias":"33.5","pid":20509,"prop_name":"尺码","sort_order":80,"status":"normal","vid":672896050},{"cid":125632002,"name":"EUR34","name_alias":"34","pid":20509,"prop_name":"尺码","sort_order":81,"status":"normal","vid":147478970},{"cid":125632002,"name":"EUR34.5","name_alias":"34.5","pid":20509,"prop_name":"尺码","sort_order":82,"status":"normal","vid":672896051},{"cid":125632002,"name":"EUR35","name_alias":"35","pid":20509,"prop_name":"尺码","sort_order":83,"status":"normal","vid":296172561},{"cid":125632002,"name":"EUR35.5","name_alias":"35.5","pid":20509,"prop_name":"尺码","sort_order":84,"status":"normal","vid":672896052},{"cid":125632002,"name":"EUR36","name_alias":"36","pid":20509,"prop_name":"尺码","sort_order":85,"status":"normal","vid":59280855},{"cid":125632002,"name":"EUR36.5","name_alias":"36.5","pid":20509,"prop_name":"尺码","sort_order":86,"status":"normal","vid":672896053},{"cid":125632002,"name":"EUR37","name_alias":"37","pid":20509,"prop_name":"尺码","sort_order":87,"status":"normal","vid":72380707},{"cid":125632002,"name":"EUR37.5","name_alias":"37.5","pid":20509,"prop_name":"尺码","sort_order":88,"status":"normal","vid":672896054},{"cid":125632002,"name":"eur38","name_alias":"38","pid":20509,"prop_name":"尺码","sort_order":89,"status":"normal","vid":103189693},{"cid":125632002,"name":"EUR38.5","name_alias":"38.5","pid":20509,"prop_name":"尺码","sort_order":90,"status":"normal","vid":672896055},{"cid":125632002,"name":"EUR39","name_alias":"39","pid":20509,"prop_name":"尺码","sort_order":91,"status":"normal","vid":418624880},{"cid":125632002,"name":"EUR39.5","name_alias":"39.5","pid":20509,"prop_name":"尺码","sort_order":92,"status":"normal","vid":672896056},{"cid":125632002,"name":"EUR40","name_alias":"40","pid":20509,"prop_name":"尺码","sort_order":93,"status":"normal","vid":229418985},{"cid":125632002,"name":"EUR40.5","name_alias":"40.5","pid":20509,"prop_name":"尺码","sort_order":94,"status":"normal","vid":672896057},{"cid":125632002,"name":"EUR41","name_alias":"41","pid":20509,"prop_name":"尺码","sort_order":95,"status":"normal","vid":407396361},{"cid":125632002,"name":"EUR41.5","name_alias":"41.5","pid":20509,"prop_name":"尺码","sort_order":96,"status":"normal","vid":672896058},{"cid":125632002,"name":"EUR42","name_alias":"42","pid":20509,"prop_name":"尺码","sort_order":97,"status":"normal","vid":473680452},{"cid":125632002,"name":"EUR42.5","name_alias":"42.5","pid":20509,"prop_name":"尺码","sort_order":98,"status":"normal","vid":69326249},{"cid":125632002,"name":"EUR43","name_alias":"43","pid":20509,"prop_name":"尺码","sort_order":99,"status":"normal","vid":225078235},{"cid":125632002,"name":"EUR43.5","name_alias":"43.5","pid":20509,"prop_name":"尺码","sort_order":100,"status":"normal","vid":672896059},{"cid":125632002,"name":"EUR44","name_alias":"44","pid":20509,"prop_name":"尺码","sort_order":101,"status":"normal","vid":64797379},{"cid":125632002,"name":"EUR44.5","name_alias":"44.5","pid":20509,"prop_name":"尺码","sort_order":102,"status":"normal","vid":672896060},{"cid":125632002,"name":"EUR45","name_alias":"45","pid":20509,"prop_name":"尺码","sort_order":103,"status":"normal","vid":481222891},{"cid":125632002,"name":"EUR45.5","name_alias":"45.5","pid":20509,"prop_name":"尺码","sort_order":104,"status":"normal","vid":672896061},{"cid":125632002,"name":"EUR46","name_alias":"46","pid":20509,"prop_name":"尺码","sort_order":105,"status":"normal","vid":662626373},{"cid":125632002,"name":"EUR46.5","name_alias":"46.5","pid":20509,"prop_name":"尺码","sort_order":106,"status":"normal","vid":672896062},{"cid":125632002,"name":"EUR47","name_alias":"47","pid":20509,"prop_name":"尺码","sort_order":107,"status":"normal","vid":672896063},{"cid":125632002,"name":"EUR47.5","name_alias":"47.5","pid":20509,"prop_name":"尺码","sort_order":108,"status":"normal","vid":672896064},{"cid":125632002,"name":"EUR48","name_alias":"48","pid":20509,"prop_name":"尺码","sort_order":109,"status":"normal","vid":662626374},{"cid":125632002,"name":"EUR48.5","name_alias":"48.5","pid":20509,"prop_name":"尺码","sort_order":110,"status":"normal","vid":801304011},{"cid":125632002,"name":"EUR50","name_alias":"50","pid":20509,"prop_name":"尺码","sort_order":110,"status":"normal","vid":70653492},{"cid":125632002,"name":"EUR49","name_alias":"49","pid":20509,"prop_name":"尺码","sort_order":111,"status":"normal","vid":182866991},{"cid":125632002,"name":"EUR52","name_alias":"52","pid":20509,"prop_name":"尺码","sort_order":111,"status":"normal","vid":662626376},{"cid":125632002,"name":"EUR49.5","name_alias":"49.5","pid":20509,"prop_name":"尺码","sort_order":112,"status":"normal","vid":801304012},{"cid":125632002,"name":"EUR54","name_alias":"54","pid":20509,"prop_name":"尺码","sort_order":112,"status":"normal","vid":662626377},{"cid":125632002,"name":"EUR50.5","name_alias":"50.5","pid":20509,"prop_name":"尺码","sort_order":113,"status":"normal","vid":801304013},{"cid":125632002,"name":"EUR51","name_alias":"51","pid":20509,"prop_name":"尺码","sort_order":114,"status":"normal","vid":801304014},{"cid":125632002,"name":"EUR51.5","name_alias":"51.5","pid":20509,"prop_name":"尺码","sort_order":115,"status":"normal","vid":801304015},{"cid":125632002,"name":"EUR52.5","name_alias":"52.5","pid":20509,"prop_name":"尺码","sort_order":116,"status":"normal","vid":801304016},{"cid":125632002,"name":"EUR53","name_alias":"53","pid":20509,"prop_name":"尺码","sort_order":117,"status":"normal","vid":801304017},{"cid":125632002,"name":"EUR53.5","name_alias":"53.5","pid":20509,"prop_name":"尺码","sort_order":118,"status":"normal","vid":801304018},{"cid":125632002,"name":"240","name_alias":"240","pid":20509,"prop_name":"尺码","sort_order":234,"status":"normal","vid":741},{"cid":125632002,"name":"245","name_alias":"245","pid":20509,"prop_name":"尺码","sort_order":236,"status":"normal","vid":3286514},{"cid":125632002,"name":"250","name_alias":"250","pid":20509,"prop_name":"尺码","sort_order":237,"status":"normal","vid":1035},{"cid":125632002,"name":"255","name_alias":"255","pid":20509,"prop_name":"尺码","sort_order":239,"status":"normal","vid":138237},{"cid":125632002,"name":"260","name_alias":"260","pid":20509,"prop_name":"尺码","sort_order":240,"status":"normal","vid":742},{"cid":125632002,"name":"265","name_alias":"265","pid":20509,"prop_name":"尺码","sort_order":242,"status":"normal","vid":3335077},{"cid":125632002,"name":"270","name_alias":"270","pid":20509,"prop_name":"尺码","sort_order":243,"status":"normal","vid":117196268},{"cid":125632002,"name":"275","name_alias":"275","pid":20509,"prop_name":"尺码","sort_order":245,"status":"normal","vid":1036},{"cid":125632002,"name":"280","name_alias":"280","pid":20509,"prop_name":"尺码","sort_order":246,"status":"normal","vid":3279326},{"cid":125632002,"name":"285","name_alias":"285","pid":20509,"prop_name":"尺码","sort_order":248,"status":"normal","vid":3322799},{"cid":125632002,"name":"290","name_alias":"290","pid":20509,"prop_name":"尺码","sort_order":249,"status":"normal","vid":1124},{"cid":125632002,"name":"295","name_alias":"295","pid":20509,"prop_name":"尺码","sort_order":251,"status":"normal","vid":3365249},{"cid":125632002,"name":"300","name_alias":"300","pid":20509,"prop_name":"尺码","sort_order":252,"status":"normal","vid":33287},{"cid":125632002,"name":"Us13","name_alias":"13","pid":20509,"prop_name":"尺码","sort_order":253,"status":"normal","vid":8200687},{"cid":125632002,"name":"305","name_alias":"305","pid":20509,"prop_name":"尺码","sort_order":254,"status":"normal","vid":1428},{"cid":125632002,"name":"US13.5","name_alias":"13.5","pid":20509,"prop_name":"尺码","sort_order":254,"status":"normal","vid":399428076}]},"request_id":"rxw4vzpttiaz"}},"cid":125632002}