{"props":{"itemprops_get_response":{"item_props":{"item_prop":[{"child_template":"","is_color_prop":false,"is_enum_prop":true,"is_input_prop":true,"is_item_prop":false,"is_key_prop":false,"is_sale_prop":true,"multi":true,"must":false,"name":"口味","parent_pid":0,"parent_vid":0,"pid":31560,"sort_order":0,"status":"normal"}]},"last_modified":"2018-07-26 16:35:47","request_id":"ektjjf30s4nf"}},"propvalues":{"itempropvalues_get_response":{"last_modified":"2018-07-26 16:35:47","prop_values":{"prop_value":[{"cid":50008432,"name":"原味","name_alias":"原味","pid":31560,"prop_name":"口味","sort_order":0,"status":"normal","vid":94572},{"cid":50008432,"name":"红枣味","name_alias":"红枣味","pid":31560,"prop_name":"口味","sort_order":0,"status":"normal","vid":17728890}]},"request_id":"132teoxl5qzwg"}},"cid":50008432}