{"props":{"itemprops_get_response":{"item_props":{"item_prop":[{"child_template":"","is_color_prop":false,"is_enum_prop":true,"is_input_prop":false,"is_item_prop":false,"is_key_prop":false,"is_sale_prop":true,"multi":true,"must":false,"name":"套餐类型","parent_pid":0,"parent_vid":0,"pid":5919063,"sort_order":0,"status":"normal"},{"child_template":"","is_color_prop":false,"is_enum_prop":true,"is_input_prop":false,"is_item_prop":false,"is_key_prop":false,"is_sale_prop":true,"multi":true,"must":false,"name":"SIM卡大小","parent_pid":0,"parent_vid":0,"pid":153558611,"sort_order":2,"status":"normal"}]},"last_modified":"2018-07-26 16:26:47","request_id":"qm3pu22syu47"}},"propvalues":{"itempropvalues_get_response":{"last_modified":"2018-07-26 16:26:47","prop_values":{"prop_value":[{"cid":50012914,"name":"套餐一","name_alias":"套餐一","pid":5919063,"prop_name":"套餐类型","sort_order":1,"status":"normal","vid":3266779},{"cid":50012914,"name":"套餐二","name_alias":"套餐二","pid":5919063,"prop_name":"套餐类型","sort_order":2,"status":"normal","vid":3266781},{"cid":50012914,"name":"套餐三","name_alias":"套餐三","pid":5919063,"prop_name":"套餐类型","sort_order":3,"status":"normal","vid":3266785},{"cid":50012914,"name":"套餐四","name_alias":"套餐四","pid":5919063,"prop_name":"套餐类型","sort_order":4,"status":"normal","vid":3266786},{"cid":50012914,"name":"套餐五","name_alias":"套餐五","pid":5919063,"prop_name":"套餐类型","sort_order":5,"status":"normal","vid":3266789},{"cid":50012914,"name":"套餐六","name_alias":"套餐六","pid":5919063,"prop_name":"套餐类型","sort_order":6,"status":"normal","vid":3284565},{"cid":50012914,"name":"套餐七","name_alias":"套餐七","pid":5919063,"prop_name":"套餐类型","sort_order":7,"status":"normal","vid":3284566},{"cid":50012914,"name":"套餐八","name_alias":"套餐八","pid":5919063,"prop_name":"套餐类型","sort_order":8,"status":"normal","vid":3284567},{"cid":50012914,"name":"套餐九","name_alias":"套餐九","pid":5919063,"prop_name":"套餐类型","sort_order":9,"status":"normal","vid":59904168},{"cid":50012914,"name":"套餐十","name_alias":"套餐十","pid":5919063,"prop_name":"套餐类型","sort_order":10,"status":"normal","vid":79046194},{"cid":50012914,"name":"套餐十一","name_alias":"套餐十一","pid":5919063,"prop_name":"套餐类型","sort_order":11,"status":"normal","vid":124062536},{"cid":50012914,"name":"套餐十二","name_alias":"套餐十二","pid":5919063,"prop_name":"套餐类型","sort_order":12,"status":"normal","vid":205594680},{"cid":50012914,"name":"普通SIM卡","name_alias":"普通SIM卡","pid":153558611,"prop_name":"SIM卡大小","sort_order":1,"status":"normal","vid":959384140},{"cid":50012914,"name":"micro SIM卡","name_alias":"micro SIM卡","pid":153558611,"prop_name":"SIM卡大小","sort_order":2,"status":"normal","vid":136786532},{"cid":50012914,"name":"nano sim卡","name_alias":"nano sim卡","pid":153558611,"prop_name":"SIM卡大小","sort_order":3,"status":"normal","vid":189510631},{"cid":50012914,"name":"三合一卡(免剪卡)","name_alias":"三合一卡(免剪卡)","pid":153558611,"prop_name":"SIM卡大小","sort_order":4,"status":"normal","vid":1199266535}]},"request_id":"qm3syay3nf03"}},"cid":50012914}