{"props":{"itemprops_get_response":{"item_props":{"item_prop":[{"child_template":"","is_color_prop":false,"is_enum_prop":true,"is_input_prop":false,"is_item_prop":false,"is_key_prop":false,"is_sale_prop":true,"multi":true,"must":false,"name":"套票有效期","parent_pid":0,"parent_vid":0,"pid":147714873,"sort_order":0,"status":"normal"},{"child_template":"","is_color_prop":false,"is_enum_prop":true,"is_input_prop":false,"is_item_prop":false,"is_key_prop":false,"is_sale_prop":true,"multi":true,"must":false,"name":"套票类别","parent_pid":0,"parent_vid":0,"pid":147340538,"sort_order":0,"status":"normal"},{"child_template":"","is_color_prop":false,"is_enum_prop":true,"is_input_prop":false,"is_item_prop":false,"is_key_prop":false,"is_sale_prop":true,"multi":true,"must":false,"name":"座位等级","parent_pid":0,"parent_vid":0,"pid":147350562,"sort_order":0,"status":"normal"}]},"last_modified":"2018-07-26 16:26:50","request_id":"3ez3k3dgzhbz"}},"propvalues":{"itempropvalues_get_response":{"last_modified":"2018-07-26 16:26:50","prop_values":{"prop_value":[{"cid":50026091,"name":"1天","name_alias":"1天","pid":147714873,"prop_name":"套票有效期","sort_order":1,"status":"normal","vid":10518540},{"cid":50026091,"name":"3天","name_alias":"3天","pid":147714873,"prop_name":"套票有效期","sort_order":2,"status":"normal","vid":7019407},{"cid":50026091,"name":"4天","name_alias":"4天","pid":147714873,"prop_name":"套票有效期","sort_order":3,"status":"normal","vid":11809862},{"cid":50026091,"name":"6天","name_alias":"6天","pid":147714873,"prop_name":"套票有效期","sort_order":4,"status":"normal","vid":11211792},{"cid":50026091,"name":"9天","name_alias":"9天","pid":147714873,"prop_name":"套票有效期","sort_order":5,"status":"normal","vid":12129668},{"cid":50026091,"name":"10天","name_alias":"10天","pid":147714873,"prop_name":"套票有效期","sort_order":6,"status":"normal","vid":7024111},{"cid":50026091,"name":"11天","name_alias":"11天","pid":147714873,"prop_name":"套票有效期","sort_order":7,"status":"normal","vid":15888192},{"cid":50026091,"name":"12天","name_alias":"12天","pid":147714873,"prop_name":"套票有效期","sort_order":8,"status":"normal","vid":9759236},{"cid":50026091,"name":"13天","name_alias":"13天","pid":147714873,"prop_name":"套票有效期","sort_order":9,"status":"normal","vid":14490856},{"cid":50026091,"name":"14天","name_alias":"14天","pid":147714873,"prop_name":"套票有效期","sort_order":10,"status":"normal","vid":7224054},{"cid":50026091,"name":"15天","name_alias":"15天","pid":147714873,"prop_name":"套票有效期","sort_order":11,"status":"normal","vid":6931239},{"cid":50026091,"name":"连续2天","name_alias":"连续2天","pid":147714873,"prop_name":"套票有效期","sort_order":12,"status":"normal","vid":797510053},{"cid":50026091,"name":"连续3天","name_alias":"连续3天","pid":147714873,"prop_name":"套票有效期","sort_order":13,"status":"normal","vid":628542643},{"cid":50026091,"name":"连续4天","name_alias":"连续4天","pid":147714873,"prop_name":"套票有效期","sort_order":14,"status":"normal","vid":797414804},{"cid":50026091,"name":"连续5天","name_alias":"连续5天","pid":147714873,"prop_name":"套票有效期","sort_order":15,"status":"normal","vid":797414228},{"cid":50026091,"name":"连续6天","name_alias":"连续6天","pid":147714873,"prop_name":"套票有效期","sort_order":16,"status":"normal","vid":1657718354},{"cid":50026091,"name":"连续7天","name_alias":"连续7天","pid":147714873,"prop_name":"套票有效期","sort_order":17,"status":"normal","vid":797390481},{"cid":50026091,"name":"连续8天","name_alias":"连续8天","pid":147714873,"prop_name":"套票有效期","sort_order":18,"status":"normal","vid":1657702493},{"cid":50026091,"name":"连续10天","name_alias":"连续10天","pid":147714873,"prop_name":"套票有效期","sort_order":19,"status":"normal","vid":1786668718},{"cid":50026091,"name":"连续14天","name_alias":"连续14天","pid":147714873,"prop_name":"套票有效期","sort_order":20,"status":"normal","vid":797356846},{"cid":50026091,"name":"连续15天","name_alias":"连续15天","pid":147714873,"prop_name":"套票有效期","sort_order":21,"status":"normal","vid":492132757},{"cid":50026091,"name":"连续21天","name_alias":"连续21天","pid":147714873,"prop_name":"套票有效期","sort_order":22,"status":"normal","vid":789328761},{"cid":50026091,"name":"连续22天","name_alias":"连续22天","pid":147714873,"prop_name":"套票有效期","sort_order":23,"status":"normal","vid":1104836691},{"cid":50026091,"name":"连续1个月","name_alias":"连续1个月","pid":147714873,"prop_name":"套票有效期","sort_order":24,"status":"normal","vid":402030726},{"cid":50026091,"name":"连续2个月","name_alias":"连续2个月","pid":147714873,"prop_name":"套票有效期","sort_order":25,"status":"normal","vid":789372335},{"cid":50026091,"name":"连续3个月","name_alias":"连续3个月","pid":147714873,"prop_name":"套票有效期","sort_order":26,"status":"normal","vid":789302846},{"cid":50026091,"name":"10天内自选2天","name_alias":"10天内自选2天","pid":147714873,"prop_name":"套票有效期","sort_order":27,"status":"normal","vid":1657767118},{"cid":50026091,"name":"10天内自选4天","name_alias":"10天内自选4天","pid":147714873,"prop_name":"套票有效期","sort_order":28,"status":"normal","vid":797458017},{"cid":50026091,"name":"14天内自选5天","name_alias":"14天内自选5天","pid":147714873,"prop_name":"套票有效期","sort_order":29,"status":"normal","vid":1657704555},{"cid":50026091,"name":"14天内自选6天","name_alias":"14天内自选6天","pid":147714873,"prop_name":"套票有效期","sort_order":30,"status":"normal","vid":1657712406},{"cid":50026091,"name":"1个月内自选1天","name_alias":"1个月内自选1天","pid":147714873,"prop_name":"套票有效期","sort_order":31,"status":"normal","vid":1955461805},{"cid":50026091,"name":"1个月内自选2天","name_alias":"1个月内自选2天","pid":147714873,"prop_name":"套票有效期","sort_order":32,"status":"normal","vid":1955461811},{"cid":50026091,"name":"1个月内自选3天","name_alias":"1个月内自选3天","pid":147714873,"prop_name":"套票有效期","sort_order":33,"status":"normal","vid":789396117},{"cid":50026091,"name":"1个月内自选4天","name_alias":"1个月内自选4天","pid":147714873,"prop_name":"套票有效期","sort_order":34,"status":"normal","vid":789344568},{"cid":50026091,"name":"1个月内自选5天","name_alias":"1个月内自选5天","pid":147714873,"prop_name":"套票有效期","sort_order":35,"status":"normal","vid":789326755},{"cid":50026091,"name":"1个月内自选6天","name_alias":"1个月内自选6天","pid":147714873,"prop_name":"套票有效期","sort_order":36,"status":"normal","vid":1955457975},{"cid":50026091,"name":"1个月内自选7天","name_alias":"1个月内自选7天","pid":147714873,"prop_name":"套票有效期","sort_order":37,"status":"normal","vid":1104822840},{"cid":50026091,"name":"1个月内自选8天","name_alias":"1个月内自选8天","pid":147714873,"prop_name":"套票有效期","sort_order":38,"status":"normal","vid":789306787},{"cid":50026091,"name":"1个月内自选10天","name_alias":"1个月内自选10天","pid":147714873,"prop_name":"套票有效期","sort_order":39,"status":"normal","vid":1786694722},{"cid":50026091,"name":"1个月内自选15天","name_alias":"1个月内自选15天","pid":147714873,"prop_name":"套票有效期","sort_order":40,"status":"normal","vid":797392453},{"cid":50026091,"name":"2个月内自选3天","name_alias":"2个月内自选3天","pid":147714873,"prop_name":"套票有效期","sort_order":41,"status":"normal","vid":1786681690},{"cid":50026091,"name":"2个月内自选4天","name_alias":"2个月内自选4天","pid":147714873,"prop_name":"套票有效期","sort_order":42,"status":"normal","vid":789340616},{"cid":50026091,"name":"2个月内自选5天","name_alias":"2个月内自选5天","pid":147714873,"prop_name":"套票有效期","sort_order":43,"status":"normal","vid":789382230},{"cid":50026091,"name":"2个月内自选6天","name_alias":"2个月内自选6天","pid":147714873,"prop_name":"套票有效期","sort_order":44,"status":"normal","vid":789292941},{"cid":50026091,"name":"2个月内自选7天","name_alias":"2个月内自选7天","pid":147714873,"prop_name":"套票有效期","sort_order":45,"status":"normal","vid":1786730707},{"cid":50026091,"name":"2个月内自选8天","name_alias":"2个月内自选8天","pid":147714873,"prop_name":"套票有效期","sort_order":46,"status":"normal","vid":789298890},{"cid":50026091,"name":"2个月内自选10天","name_alias":"2个月内自选10天","pid":147714873,"prop_name":"套票有效期","sort_order":47,"status":"normal","vid":789298896},{"cid":50026091,"name":"2个月内自选15天","name_alias":"2个月内自选15天","pid":147714873,"prop_name":"套票有效期","sort_order":48,"status":"normal","vid":789406166},{"cid":50026091,"name":"1个月自选4段","name_alias":"1个月自选4段","pid":147714873,"prop_name":"套票有效期","sort_order":49,"status":"normal","vid":1786699720},{"cid":50026091,"name":"1个月自选6段","name_alias":"1个月自选6段","pid":147714873,"prop_name":"套票有效期","sort_order":50,"status":"normal","vid":1786736736},{"cid":50026091,"name":"1个月自选8段","name_alias":"1个月自选8段","pid":147714873,"prop_name":"套票有效期","sort_order":51,"status":"normal","vid":1786700702},{"cid":50026091,"name":"1个月自选10段","name_alias":"1个月自选10段","pid":147714873,"prop_name":"套票有效期","sort_order":52,"status":"normal","vid":1786665721},{"cid":50026091,"name":"点对点单程","name_alias":"点对点单程","pid":147714873,"prop_name":"套票有效期","sort_order":53,"status":"normal","vid":200231054},{"cid":50026091,"name":"点对点往返","name_alias":"点对点往返","pid":147714873,"prop_name":"套票有效期","sort_order":54,"status":"normal","vid":200239047},{"cid":50026091,"name":"儿童","name_alias":"儿童","pid":147340538,"prop_name":"套票类别","sort_order":0,"status":"normal","vid":27845},{"cid":50026091,"name":"长者","name_alias":"长者","pid":147340538,"prop_name":"套票类别","sort_order":0,"status":"normal","vid":62960307},{"cid":50026091,"name":"青少年","name_alias":"青少年","pid":147340538,"prop_name":"套票类别","sort_order":1,"status":"normal","vid":42007},{"cid":50026091,"name":"成人","name_alias":"成人","pid":147340538,"prop_name":"套票类别","sort_order":2,"status":"normal","vid":3622544},{"cid":50026091,"name":"儿童（一名成人可携两名儿童）","name_alias":"儿童（一名成人可携两名儿童）","pid":147340538,"prop_name":"套票类别","sort_order":3,"status":"normal","vid":790344097},{"cid":50026091,"name":"2-5名成人同行（按人数拍）","name_alias":"2-5名成人同行（按人数拍）","pid":147340538,"prop_name":"套票类别","sort_order":4,"status":"normal","vid":790230978},{"cid":50026091,"name":"3-9名成人同行(按人数拍)","name_alias":"3-9名成人同行(按人数拍)","pid":147340538,"prop_name":"套票类别","sort_order":5,"status":"normal","vid":1980582898},{"cid":50026091,"name":"2名成人同行","name_alias":"2名成人同行","pid":147340538,"prop_name":"套票类别","sort_order":6,"status":"normal","vid":2228292492},{"cid":50026091,"name":"商务车厢","name_alias":"商务车厢","pid":147350562,"prop_name":"座位等级","sort_order":0,"status":"normal","vid":1657731181},{"cid":50026091,"name":"标准车厢","name_alias":"标准车厢","pid":147350562,"prop_name":"座位等级","sort_order":0,"status":"normal","vid":107576957},{"cid":50026091,"name":"1等舱","name_alias":"1等舱","pid":147350562,"prop_name":"座位等级","sort_order":1,"status":"normal","vid":788946263},{"cid":50026091,"name":"2等舱","name_alias":"2等舱","pid":147350562,"prop_name":"座位等级","sort_order":2,"status":"normal","vid":788948286},{"cid":50026091,"name":"普通席","name_alias":"普通席","pid":147350562,"prop_name":"座位等级","sort_order":3,"status":"normal","vid":14674010},{"cid":50026091,"name":"软席","name_alias":"软席","pid":147350562,"prop_name":"座位等级","sort_order":4,"status":"normal","vid":104496934},{"cid":50026091,"name":"特等座","name_alias":"特等座","pid":147350562,"prop_name":"座位等级","sort_order":5,"status":"normal","vid":200233163}]},"request_id":"ry1f2zvald1s"}},"cid":50026091}